{
	"pattrstorage": {
		"name": "u100008877",
		"slots": {
			"1": {
				"id": 1,
				"data": {
					"pitch-shift::bypass": [0],
					"pitch-shift::mix": [50.0],
					"pitch-shift::pitch_shift": [0.0],
					"pitch-shift::tuning_preset": [0],
					"pitch-shift::vibrato_amount": [0.0],
					"pitch-shift::vibrato_rate": [1.0],
					"hex-fuzz::asymmetry": [0.0],
					"hex-fuzz::bypass": [0],
					"hex-fuzz::distortion_amount": [0.5],
					"hex-fuzz::gain": [0.0],
					"hex-fuzz::mix": [50.0],
					"hex-fuzz::spread": [0.0],
					"hex-fuzz::tone": [2000.0],
					"hex-fuzz::waveshape": [0],
					"stereo-imager::depth": [0.5],
					"stereo-imager::lfo_manual": [0],
					"stereo-imager::linear_logarithmic": [0],
					"stereo-imager::offset": [0.0],
					"stereo-imager::rate": [0.5],
					"stereo-imager::spread": [0.0],
					"spread_lfo::conitnuous_discrete": [0],
					"spread_lfo::depth": [0.0, 0.2, 0.4, 0.6, 0.8, 1.0],
					"spread_lfo::invert": [0],
					"spread_lfo::linear_logarithmic": [0],
					"spread_lfo::max": [1.0],
					"spread_lfo::min": [0.0],
					"spread_lfo::rate": [0.5],
					"spread_lfo::spread": [0.0],
					"hex-tone::bypass": [0],
					"hex-tone::frequency": [2000.0],
					"hex-tone::gain": [0.0],
					"hex-tone::resonance": [1.0],
					"harmonic-tremolo::LFO_source": [1],
					"harmonic-tremolo::bypass": [0],
					"harmonic-tremolo::depth": [0.0, 0.2, 0.4, 0.6, 0.8, 1.0],
					"harmonic-tremolo::octave_harmonic": [-3.0],
					"buffer-delay::bypass": [0],
					"buffer-delay::delay_time": [500.0],
					"buffer-delay::feedback": [0.25],
					"buffer-delay::mix": [50.0],
					"buffer-delay::reverse_fade": [0.25],
					"buffer-delay::reverse_toggle": [0],
					"buffer-delay::spread": [0.0],
					"buffer-delay::tone": [2000.0],
					"enveloper::attack": [500.0],
					"enveloper::bypass": [0],
					"enveloper::curvature": [2.0],
					"enveloper::release": [300.0],
					"enveloper::sustain": [300.0],
					"enveloper::threshold": [-70.0],
					"volume-pedal::conitnuous_discrete": [0],
					"volume-pedal::linear_logarithmic": [0],
					"volume-pedal::max": [1.0],
					"volume-pedal::min": [0.0],
					"spread::conitnuous_discrete": [0],
					"spread::linear_logarithmic": [0],
					"spread::max": [1.0],
					"spread::min": [0.0],
					"spread::multislider": [0.0, 0.2, 0.4, 0.6, 0.8, 1.0]
				}
			}
		}
	}
}
